torchtrace/__init__.py
torchtrace/__main__.py
torchtrace/base.py
torchtrace/init.py
torchtrace/nn.py
torchtrace/optim.py
torchtrace/test.py
torchtrace/tracer.py
torchtrace/utils.py
torchtrace-0.2.dist-info/METADATA
torchtrace-0.2.dist-info/WHEEL
torchtrace-0.2.dist-info/top_level.txt
torchtrace-0.2.dist-info/RECORD
