Metadata-Version: 2.1
Name: torchtrace
Version: 0.2
Summary: A simple autograd implementation based on PyTorch
Home-page: https://github.com/gusye1234/PyTrace
Author: 
